nemoview/__init__.py
nemoview/__main__.py
nemoview/__version__.py
nemoview/dashstyle.mplstyle
nemoview/nemodash.ipynb
nemoview/visualization.py
nemoview/widgets.py
nemoview/figs/favicon.ico
nemoview/figs/nemoview.png
nemoview-0.3.3.dist-info/licenses/LICENSE
nemoview-0.3.3.dist-info/METADATA
nemoview-0.3.3.dist-info/WHEEL
nemoview-0.3.3.dist-info/entry_points.txt
nemoview-0.3.3.dist-info/top_level.txt
nemoview-0.3.3.dist-info/RECORD
