Metadata-Version: 2.4
Name: nemoview
Version: 0.3.3
Summary: Visualization tool for NEMO ensembles
Author-email: Leonardo Evaristo de Sousa <ledso@dtu.dk>
License-Expression: MIT
Project-URL: Homepage, https://github.com/LeonardoESousa/nemoview
Requires-Python: >=3.8.0
License-File: LICENSE
Requires-Dist: matplotlib==3.9.0
Requires-Dist: voila==0.5.7
Requires-Dist: ipywidgets==8.1.3
Requires-Dist: pandas==1.5.3
Requires-Dist: IPython
Requires-Dist: Ipympl
Requires-Dist: jinja2
Requires-Dist: nemophoto>=1.3.2
Requires-Dist: ipykernel==6.29.5
Requires-Dist: numpy==1.26.4
Requires-Dist: colour-science==0.4.6
Dynamic: license-file
